{
  "title": "VAT determination request body",
  "type": "object",
  "properties": {
    "transactionData": {
      "type": "object",
      "properties": {
        "date": {
          "type": "object",
          "properties": {
            "dateOfTransaction": {
              "type": "string",
              "format": "date",
              "description": "What is the date of the transaction?"
            },
            "docDate": {
              "type": "string",
              "format": "date",
              "description": "What is the date of the document?"
            },
            "supplyDate": {
              "type": "string",
              "format": "date",
              "description": "Date of supply of good or service?"
            },
            "paymentDate": {
              "type": "string",
              "format": "date",
              "description": "What is the date of payment?"
            }
          }
        },
        "seller": {
          "type": "string",
          "description": ""
        },
        "item": {
          "type": "object",
          "properties": {
            "totalAmount": {
              "type": "string",
              "description": "What is the document total?"
            },
            "itemID": {
              "type": "string",
              "description": "What is the ID of the item?"
            },
            "itemType": {
              "type": "string",
              "enum": [
                "Accommodation for business associates",
                "Accommodation for employees",
                "Accountancy service",
                "Activities carried out by television and radio bodies (non-commercial)",
                "Admission to a cinema",
                "Admission to a circus",
                "Admission to a concert or theatre",
                "Admission to a sporting event",
                "Admission to amusement parks",
                "Admission to events",
                "Advertising services",
                "Aircraft",
                "Air freight",
                "Alcohol",
                "Aluminium",
                "Animal foodstuffs",
                "Antiques",
                "Architecture services",
                "Baby food and processed food stuff",
                "Banking",
                "Bedding plants, seeds, fertilizers and other agrochemical products",
                "Beer",
                "Betting",
                "Beverages (non-alcoholic)",
                "Books",
                "Books (educational only)",
                "Bread",
                "Broadcasting services",
                "Bus",
                "Car",
                "Cattle food",
                "Cereals",
                "Chemicals",
                "Children's car seats",
                "Children's clothing",
                "Clothing",
                "CO2 emission rights",
                "Cocoa beans, whole or broken, raw or roasted",
                "Coconuts, Brazil nuts and cashew nuts",
                "Coffee, not roasted",
                "Collectors' items",
                "Computers and peripheral equipment",
                "Construction of social dwellings",
                "Construction work, including repair, cleaning, maintenance, demolition",
                "Construction, errection or housing used on a permanent residence",
                "Consultancy service",
                "Copper",
                "Courier service",
                "Cultural, sporting and exhibition services",
                "Data processing",
                "Demolition and rebuilding of houses in major cities",
                "Dental services",
                "Development and sale of non-standard Software",
                "Diesel",
                "Digital service",
                "Disbursement",
                "eBook",
                "Edible oils",
                "Education",
                "Electricity",
                "Electronically supplied services",
                "Estate agency services",
                "Extended warranty",
                "Financial services that aren't exempt",
                "Food and beverage (non-alcoholic)",
                "Footwear",
                "Fuel",
                "Gas and electricity certificates",
                "Gas through a natural gas system",
                "Geological materials",
                "Goods for the equipping, fuelling and provisioning of pleasure boats and private aircraft or any other means of transport for private use",
                "Goods supplied on board train, vessel or aircraft",
                "Goods supplied with installation",
                "GP services",
                "Grains and oil seeds (including soya beans) and oleaginous fruits",
                "Hairdressing services",
                "Haulage services",
                "Heating or cooling energy through networks",
                "Hire of a motor vehicle",
                "Hire of a vessel",
                "Hire of an aircraft",
                "Hire of goods",
                "Holiday camp accommodation",
                "Hospital care",
                "Hotel accommodation",
                "Human organs, blood and milk",
                "Husked rice",
                "Installation services",
                "Insurance",
                "Integrated circuit devices or computer chips",
                "Investment gold",
                "Land",
                "Lawyer's service",
                "Lead",
                "Leasing of a building",
                "Letting of a building",
                "Letting agency services",
                "Livestock",
                "Lorry",
                "Lotteries",
                "Machinery",
                "Magazines",
                "Marketing",
                "Media streaming",
                "Medical equipment",
                "Medication",
                "Milk",
                "Mineral oils (including propane and butane; also including crude petroleum oils)",
                "Miscellaneous goods",
                "Mobile phone",
                "Modification, repair or maintenance of a vessel",
                "Modification, repair or maintenance of an aircraft",
                "Motorbike",
                "Movable, tangible property",
                "Newspaper or periodical publishing service",
                "Newspapers",
                "Nickel",
                "Old, used, scrap materials",
                "Olives",
                "Organising of events",
                "Other event services",
                "Other nuts",
                "Other services",
                "Payment Services",
                "Periodicals",
                "Petrol",
                "Pharmaceutical products",
                "Photographs and other printed matter",
                "Platinum (palladium, rhodium)",
                "Postal services",
                "Potatoes",
                "Private tuition",
                "Provision of information",
                "Raw or semi-finished metals (not scrap metals)",
                "Raw sugar",
                "Refuelling aircraft",
                "Refuelling vessels",
                "Reinsurance",
                "Renovation and repair of private dwellings",
                "Renovation of houses over 10 years old",
                "Repair and maintenance services",
                "Restaurant and catering services",
                "Restaurant and catering services on board a ship, aircraft or train",
                "Rubber, in primary forms or in plates, sheets or strip",
                "Sea freight",
                "Services connected to sports competitions and games of chance",
                "Services linked to sport or physical education by non-profit making orangisations",
                "Services linked to welfare and social security",
                "Services of consultants, engineers, consultancy firms, lawyers, accountants and other similar services, as well as data processing and the provision of information",
                "Services rendered by operators of museums, botanical gardens and zoos",
                "Services Supplied by Travel Agents",
                "Services to disabled persons",
                "Silver",
                "Small repair services to bicycles, shoes and clothing",
                "Social care for children",
                "Social housing",
                "Spirits",
                "Stamps",
                "Storage services",
                "Supplies for goods or passenger transport",
                "Supply of services linked to protection of children and young persons",
                "Supply of a building",
                "Supply of staff by religious or philosophical institutions for children's education",
                "Supply of staff by religious or philosophical institutions for hospital and medical care",
                "Supply of staff by religious or philosophical institutions for the protection of children and young persons",
                "Supply of staff by religious or philosophical institutions for welfare and social security work",
                "Takeway food",
                "Tea",
                "Telecommunications services",
                "Textiles",
                "The granting and negotiation of credit",
                "The hire of safes",
                "The hiring out of moveable tangible property (excluding means of transport)",
                "The letting of permanently installed equipment and machinery",
                "The letting of premises and sites for the parking of vehicles",
                "The management of special investment funds as defined by Member States",
                "The negotiation of or any dealings in credit guarantees or any other security for money and the management of credit guarantees by the person who is granting the credit",
                "The provision of access to a natural gas system situated within the territory of the Community or to any network connected to such a system",
                "The supply of staff",
                "The supply of staff engaged in construction work",
                "Tin",
                "Tobacco",
                "Train",
                "Training (with admittance)",
                "Training (privately contracted)",
                "Training (online)",
                "Transactions, including negotiation but not management or safekeeping, in shares, interests in companies or associations, debentures and other securities, but excluding documents establishing title to goods, and the rights or securities",
                "Transactions, including negotiation, concerning currency, bank notes and coins used as legal tender, with the exception of collectors' items",
                "Transactions, including negotiation, concerning deposit and current accounts, payments, transfers, debts, cheques and other negotiable instruments, but excluding debt collection",
                "Transfers and assignments of copyrights, patents, licences, trade marks and similar rights",
                "Transport services for sick or injured people (ambulance)",
                "Transport services such as loading, handling, unloading",
                "Transportation of persons by air",
                "Transportation of persons by land",
                "Transportation of persons by sea",
                "Truck",
                "Urns and coffins",
                "Use of sporting facilities",
                "Valuation of movable proprty",
                "Van",
                "Vegetable oils and fats and their fractions, whether or not refined, but not chemically modified",
                "Vessel",
                "Vetinary services",
                "Video games, games consoles, laptops, tablets",
                "Waste collection",
                "Water (non-branded)",
                "Wine",
                "Wool",
                "Work on movable property",
                "Works of art",
                "Writers, composers, etc",
                "Zinc"
              ],
              "description": "Item"
            },
            "reversedVatRate": {
              "type": "string",
              "description": "Reversed VAT rate percentage?"
            },
            "vatRate": {
              "type": "string",
              "description": "VAT rate percentage?"
            },
            "description": {
              "type": "string",
              "description": "Item description"
            },
            "totalAmountCurrency2": {
              "type": "string",
              "description": "What is the document total in crrency 2?"
            },
            "itemDeductionRate": {
              "type": "string",
              "description": "What is the item deduction rate?"
            },
            "rateCategory": {
              "type": "string",
              "description": "What is the VAT rate category?"
            },
            "importVatAmount": {
              "type": "string",
              "description": "What is the import VAT amount on the customs document?"
            },
            "value": {
              "type": "string",
              "description": "What is the amount of the item?"
            },
            "vatAmount": {
              "type": "string",
              "description": "What is the VAT amount of the item?"
            }
          }
        },
        "thirdParties": {
          "type": "object",
          "properties": {
            "mpEstablishedCountry": {
              "type": "string",
              "minLength": 2,
              "maxLength": 2,
              "example": "GB",
              "description": "In which country is the marketplace established?"
            },
            "mpRegisteredForIOSS": {
              "type": "boolean",
              "description": "Is the marketplace registered for IOSS?"
            },
            "isMarketplace": {
              "type": "boolean",
              "description": "From marketplace perspective?"
            },
            "mpRegisteredForOSS": {
              "type": "boolean",
              "description": "Is the marketplace registered for OSS?"
            },
            "partyCEstablishmentCountry": {
              "type": "string",
              "minLength": 2,
              "maxLength": 2,
              "example": "GB",
              "description": "Establishment country of Party C"
            },
            "intermediaryRegisteredForIOSS": {
              "type": "boolean",
              "description": "Is the intermediary registered for IOSS?"
            },
            "partyCVatIdCountry": {
              "type": "string",
              "minLength": 2,
              "maxLength": 2,
              "example": "GB",
              "description": "VAT ID country of Party C"
            },
            "carrierRegisteredForSpecialArrangements": {
              "type": "boolean",
              "description": "Is the carrier registered for Special Arrangements?"
            }
          }
        },
        "document": {
          "type": "object",
          "properties": {
            "quantity": {
              "type": "string",
              "description": "Quantity"
            },
            "docNumber": {
              "type": "string",
              "description": "What is the document number?"
            },
            "exchangeRate": {
              "type": "string",
              "description": "What is the exchange rate?"
            },
            "docType": {
              "type": "string",
              "enum": [
                "Sales invoice",
                "Sales credit",
                "Purchase invoice",
                "Purchase credit",
                "Import document",
                "Import corrective document",
                "Self-bill sale",
                "Self-bill sale credit",
                "Self-bill purchase",
                "Self-bill purchase credit",
                "Sales transfer",
                "Sales transfer credit",
                "Purchase transfer",
                "Purchase transfer credit",
                "Sales order",
                "Sales order credit",
                "Purchase order",
                "Purchase order credit"
              ],
              "description": "Type of document"
            },
            "discount": {
              "type": "string",
              "description": "Discount percentage?"
            },
            "currency": {
              "type": "string",
              "description": "What is the currency on the document?"
            },
            "lineNumber": {
              "type": "string",
              "description": "Line number on the document"
            }
          }
        },
        "itemProperties": {
          "type": "object",
          "properties": {
            "isServicesConnectedWithImmovableProperty": {
              "type": "boolean",
              "description": "is ServicesConnectedWithImmovableProperty?"
            },
            "isAncillaryServicesRelatingToCulturalArtisticSportingScientificEducationalEntertainmentFairsExhibitionsOrSimilarActivities": {
              "type": "boolean",
              "description": "is AncillaryServicesRelatingToCulturalArtisticSportingScientificEducationalEntertainmentFairsExhibitionsOrSimilarActivities?"
            },
            "isImmovableProperty": {
              "type": "boolean",
              "description": "is ImmovableProperty?"
            },
            "isDigitalService": {
              "type": "boolean",
              "description": "is DigitalService?"
            },
            "isSuppliedByIntermediary": {
              "type": "boolean",
              "description": "is SuppliedByIntermediary?"
            },
            "isOnboardShipAircraftTrain": {
              "type": "boolean",
              "description": "on board ship, aircraft ot train?"
            },
            "isWelfareAndSocialSecurity": {
              "type": "boolean",
              "description": "is WelfareAndSocialSecurity?"
            },
            "isTransportationOfPersons": {
              "type": "boolean",
              "description": "is TransportationOfPersons?"
            },
            "isCapitalGood": {
              "type": "boolean",
              "description": "is CapitalGood?"
            },
            "isGambling": {
              "type": "boolean",
              "description": "is Gambling?"
            },
            "isHireMeansOfTransport": {
              "type": "boolean",
              "description": "is HireMeansOfTransport?"
            },
            "isValuationsOfAndWorkOnMoveableProperty": {
              "type": "boolean",
              "description": "is ValuationsOfAndWorkOnMoveableProperty?"
            },
            "isArticle59Service": {
              "type": "boolean",
              "description": "is Article59Service?"
            },
            "isMovableProperty": {
              "type": "boolean",
              "description": "is MovableProperty?"
            },
            "isService": {
              "type": "boolean",
              "description": "is Service?"
            },
            "isAdmission": {
              "type": "boolean",
              "description": "is Admission?"
            },
            "isAccommodation": {
              "type": "boolean",
              "description": "is Accommodation?"
            },
            "isInsuranceOrReinsurance": {
              "type": "boolean",
              "description": "is InsuranceOrReinsurance?"
            },
            "isPublicPostalService": {
              "type": "boolean",
              "description": "is PublicPostalService?"
            },
            "isSecondHand": {
              "type": "boolean",
              "description": "is second hand?"
            },
            "isGood": {
              "type": "boolean",
              "description": "is Good?"
            },
            "isTheSupplyOfStaffServices": {
              "type": "boolean",
              "description": "is TheSupplyOfStaffServices?"
            },
            "isNewMeansOfTransport": {
              "type": "boolean",
              "description": "is NewMeansOfTransport?"
            },
            "isGasElectricityHeatingCooling": {
              "type": "boolean",
              "description": "is GasElectricityHeatingCooling?"
            },
            "isTransportationOfGoods": {
              "type": "boolean",
              "description": "is TransportationOfGoods?"
            },
            "isFinancialService": {
              "type": "boolean",
              "description": "is FinancialService?"
            },
            "isEducation": {
              "type": "boolean",
              "description": "is Education?"
            },
            "isAncillaryTransportServices": {
              "type": "boolean",
              "description": "is AncillaryTransportServices?"
            },
            "isExciseGood": {
              "type": "boolean",
              "description": "is ExciseGood?"
            },
            "isRestaurantOrCateringService": {
              "type": "boolean",
              "description": "is RestaurantOrCateringService?"
            },
            "isMedicalCare": {
              "type": "boolean",
              "description": "is MedicalCare?"
            }
          }
        },
        "locations": {
          "type": "object",
          "properties": {
            "shipFrom": {
              "type": "string",
              "minLength": 2,
              "maxLength": 2,
              "example": "GB",
              "description": "What is the ship from?"
            },
            "placeOfGoods": {
              "type": "string",
              "minLength": 2,
              "maxLength": 2,
              "example": "GB",
              "description": "What is the place of the goods?"
            },
            "departureCountry": {
              "type": "string",
              "minLength": 2,
              "maxLength": 2,
              "example": "GB",
              "description": "What is the country of departure?"
            },
            "countryImport": {
              "type": "string",
              "minLength": 2,
              "maxLength": 2,
              "example": "GB",
              "description": "What is the country of importation?"
            },
            "placeOfService": {
              "type": "string",
              "minLength": 2,
              "maxLength": 2,
              "example": "GB",
              "description": "Where was the service carried out?"
            },
            "arrivalCountry": {
              "type": "string",
              "minLength": 2,
              "maxLength": 2,
              "example": "GB",
              "description": "What is the country of arrival?"
            },
            "shipTo": {
              "type": "string",
              "minLength": 2,
              "maxLength": 2,
              "example": "GB",
              "description": "Ship to"
            }
          }
        },
        "transportTerms": {
          "type": "object",
          "properties": {
            "importerOfRecord": {
              "type": "string",
              "enum": [
                "Seller",
                "Buyer"
              ],
              "description": "Which party is the importer?"
            },
            "consignmentValue": {
              "type": "string",
              "description": "Value of the consignment?"
            },
            "transport": {
              "type": "string",
              "enum": [
                "Seller",
                "Buyer",
                "Third-party on behalf of seller",
                "Third-party on behalf of buyer",
                "None"
              ],
              "description": "Which party takes care of the transport?"
            }
          }
        },
        "transactionDetail": {
          "type": "object",
          "properties": {
            "isBusinessEntertainment": {
              "type": "boolean",
              "description": "For business entertainment"
            },
            "isForProvisioningOfVessel": {
              "type": "boolean",
              "description": "For the provisioning of a vessel?"
            },
            "isFreeZone": {
              "type": "boolean",
              "description": "Goods placed in free zone?"
            },
            "isExternalTransit": {
              "type": "boolean",
              "description": "Goods under external transit procedure?"
            },
            "isDonatedItem": {
              "type": "boolean",
              "description": "Is/Was the item donated to the charity?"
            },
            "isCustomsWarehouse": {
              "type": "boolean",
              "description": "Goods placed in customs warehouse?"
            },
            "warehouseFiscalRepresentative": {
              "type": "boolean",
              "description": "Appointed local fiscal representative?"
            },
            "customsDutyAndLevyAmount": {
              "type": "string",
              "description": "Other duties taxes and levies on import"
            },
            "optedNotToTax": {
              "type": "boolean",
              "description": "Has the supplier opted not to tax?"
            },
            "optedToTax": {
              "type": "boolean",
              "description": "Has the supplier opted to tax?"
            },
            "durationOfHire": {
              "type": "string",
              "description": "Duration of hire (days)?"
            },
            "callOffStock": {
              "type": "boolean",
              "description": "Are the goods supplied under a call-off stock arrangement?"
            },
            "insuranceAmount": {
              "type": "string",
              "description": "Insurance amount"
            },
            "shippingAndHandlingAmount": {
              "type": "string",
              "description": "Shipping and handling amount"
            },
            "isTemporaryStorage": {
              "type": "boolean",
              "description": "Goods placed under temporary storage?"
            },
            "betweenContractors": {
              "type": "boolean",
              "description": "Transaction between two contractors?"
            },
            "importedUnderDefermentScheme": {
              "type": "boolean",
              "description": "Are the goods imported under an import VAT deferment scheme?"
            },
            "soldOnMarketplace": {
              "type": "boolean",
              "description": "Sold on a marketplace?"
            },
            "isForProvisioningOfAirline": {
              "type": "boolean",
              "description": "For the provisioning of an airline?"
            },
            "isInwardProcessing": {
              "type": "boolean",
              "description": "Goods placed under inward processing?"
            },
            "relevantContractsTax": {
              "type": "boolean",
              "description": "Under Relevant Contracts Tax / CIS?"
            },
            "isCustomsProcedure": {
              "type": "boolean",
              "description": "Goods placed under customs procedure?"
            },
            "isVatWarehouse": {
              "type": "boolean",
              "description": "Goods into / removed from a VAT warehouse?"
            },
            "cashAccounting": {
              "type": "boolean",
              "description": "Using cash accounting?"
            },
            "linkedToExport": {
              "type": "boolean",
              "description": "is the transaction related to an export?"
            },
            "isSuccessiveSupply": {
              "type": "boolean",
              "description": "Part of a successive (chain) supply?"
            }
          }
        },
        "buyer": {
          "type": "string",
          "description": ""
        }
      }
    }
  }
}